{"data": [{"dealImage": "data:image/png;base64,R0lGODlhAQABAAD/ACwAAAAAAQABAAACADs=", "rating": "4", "title": " 10% off ", "dealUrl": "https://www.grabon.in/coupon-codes/10393", "provider": "Grabon", "shortDescription": " Kotak Mahindra Bank Offer - Grab 10% Discount on Movie Ticket ", "price": "ACTIVATE OFFER"}, {"dealImage": "data:image/png;base64,R0lGODlhAQABAAD/ACwAAAAAAQABAAACADs=", "rating": "4", "title": " 15% off ", "dealUrl": "https://www.grabon.in/coupon-codes/12301", "provider": "Grabon", "shortDescription": " Flat 15% MobiKwik SuperCash on Movie Tickets + Food & Bevarage ", "price": "ACTIVATE OFFER"}, {"dealImage": "data:image/png;base64,R0lGODlhAQABAAD/ACwAAAAAAQABAAACADs=", "rating": "3", "title": " 20% off ", "dealUrl": "https://www.grabon.in/coupon-codes/10392", "provider": "Grabon", "shortDescription": " Pay With Yes Bank Debit Card - Get 20% Discount On Big Cinemas ", "price": "ACTIVATE OFFER"}, {"dealImage": "data:image/png;base64,R0lGODlhAQABAAD/ACwAAAAAAQABAAACADs=", "rating": "3", "title": " 20% off ", "dealUrl": "https://www.grabon.in/coupon-codes/11807", "provider": "Grabon", "shortDescription": " Regular Deposits: Get Flat 20% Bonus ", "price": "ACTIVATE OFFER"}, {"dealImage": "data:image/png;base64,R0lGODlhAQABAAD/ACwAAAAAAQABAAACADs=", "rating": "4", "title": " 20% off ", "dealUrl": "https://www.grabon.in/coupon-codes/20593", "provider": "Grabon", "shortDescription": " Get 20% OFF on Events and Plays Using IndusInd Credit Card ", "price": "ACTIVATE OFFER"}, {"dealImage": "data:image/png;base64,R0lGODlhAQABAAD/ACwAAAAAAQABAAACADs=", "rating": "3", "title": " 25% off ", "dealUrl": "https://www.grabon.in/coupon-codes/20766", "provider": "Grabon", "shortDescription": " Get 25% oFF With HDFC Bank Timescard on BookMyShow ", "price": "ACTIVATE OFFER"}, {"dealImage": "data:image/png;base64,R0lGODlhAQABAAD/ACwAAAAAAQABAAACADs=", "rating": "4", "title": " 28% off ", "dealUrl": "https://www.grabon.in/coupon-codes/13981", "provider": "Grabon", "shortDescription": " Keyboards: Upto 28% OFF ", "price": "ACTIVATE OFFER"}, {"dealImage": "data:image/png;base64,R0lGODlhAQABAAD/ACwAAAAAAQABAAACADs=", "rating": "3", "title": " 30% off ", "dealUrl": "https://www.grabon.in/coupon-codes/19684", "provider": "Grabon", "shortDescription": " Get 30% OFF on Purchasing 10 Songs ", "price": "ACTIVATE OFFER"}, {"dealImage": "data:image/png;base64,R0lGODlhAQABAAD/ACwAAAAAAQABAAACADs=", "rating": "3", "title": " 5% off ", "dealUrl": "https://www.grabon.in/coupon-codes/4997", "provider": "Grabon", "shortDescription": " HDFC Bank Debit Cards | Get 5% Cashback ", "price": "ACTIVATE OFFER"}, {"dealImage": "data:image/png;base64,R0lGODlhAQABAAD/ACwAAAAAAQABAAACADs=", "rating": "4", "title": " 5% off ", "dealUrl": "https://www.grabon.in/coupon-codes/14513", "provider": "Grabon", "shortDescription": " Get Double Bonus On Your First Deposit ", "price": "ACTIVATE OFFER"}, {"dealImage": "data:image/png;base64,R0lGODlhAQABAAD/ACwAAAAAAQABAAACADs=", "rating": "4", "title": " 50% off ", "dealUrl": "https://www.grabon.in/coupon-codes/14568", "provider": "Grabon", "shortDescription": " Buy 20 Songs & Get Flat 50% OFF ", "price": "ACTIVATE OFFER"}, {"dealImage": "data:image/png;base64,R0lGODlhAQABAAD/ACwAAAAAAQABAAACADs=", "rating": "4", "title": " 50% off ", "dealUrl": "https://www.grabon.in/coupon-codes/14576", "provider": "Grabon", "shortDescription": " Get Up To 50% OFF On Movie Tickets (DBS Debit Card Users) ", "price": "ACTIVATE OFFER"}, {"dealImage": "data:image/png;base64,R0lGODlhAQABAAD/ACwAAAAAAQABAAACADs=", "rating": "4", "title": " 60% off ", "dealUrl": "https://www.grabon.in/coupon-codes/27702", "provider": "Grabon", "shortDescription": " JBL Headphones - Up to 60% OFF ", "price": "ACTIVATE OFFER"}, {"dealImage": "data:image/png;base64,R0lGODlhAQABAAD/ACwAAAAAAQABAAACADs=", "rating": "4", "title": " Best Price ", "dealUrl": "https://www.grabon.in/coupon-codes/2788", "provider": "Grabon", "shortDescription": " Purchase PVR Gift Card Offer at Discounted Price ", "price": "ACTIVATE OFFER"}, {"dealImage": "data:image/png;base64,R0lGODlhAQABAAD/ACwAAAAAAQABAAACADs=", "rating": "3", "title": " Best Price ", "dealUrl": "https://www.grabon.in/coupon-codes/8656", "provider": "Grabon", "shortDescription": " PVR Gift Cards | Starting at \u20b9500 | All Users ", "price": "ACTIVATE OFFER"}, {"dealImage": "data:image/png;base64,R0lGODlhAQABAAD/ACwAAAAAAQABAAACADs=", "rating": "4", "title": " Best Price ", "dealUrl": "https://www.grabon.in/coupon-codes/10396", "provider": "Grabon", "shortDescription": " Book NTR Kathanayakudu (Telugu) at Lowest Price ", "price": "ACTIVATE OFFER"}, {"dealImage": "data:image/png;base64,R0lGODlhAQABAAD/ACwAAAAAAQABAAACADs=", "rating": "4", "title": " Best Price ", "dealUrl": "https://www.grabon.in/coupon-codes/10434", "provider": "Grabon", "shortDescription": " Best Price For Movie Tickets ", "price": "ACTIVATE OFFER"}, {"dealImage": "data:image/png;base64,R0lGODlhAQABAAD/ACwAAAAAAQABAAACADs=", "rating": "4", "title": " Best Price ", "dealUrl": "https://www.grabon.in/coupon-codes/10472", "provider": "Grabon", "shortDescription": " Best Price For Movie Ticket Online ", "price": "ACTIVATE OFFER"}, {"dealImage": "data:image/png;base64,R0lGODlhAQABAAD/ACwAAAAAAQABAAACADs=", "rating": "3", "title": " Best Price ", "dealUrl": "https://www.grabon.in/coupon-codes/10486", "provider": "Grabon", "shortDescription": " URI - The Surgical Strike Movie Tickets @ Best Price ", "price": "ACTIVATE OFFER"}, {"dealImage": "data:image/png;base64,R0lGODlhAQABAAD/ACwAAAAAAQABAAACADs=", "rating": "4", "title": " Best Price ", "dealUrl": "https://www.grabon.in/coupon-codes/11779", "provider": "Grabon", "shortDescription": " Free Sign Up : Get Started Now ", "price": "ACTIVATE OFFER"}, {"dealImage": "data:image/png;base64,R0lGODlhAQABAAD/ACwAAAAAAQABAAACADs=", "rating": "4", "title": " Best Price ", "dealUrl": "https://www.grabon.in/coupon-codes/11806", "provider": "Grabon", "shortDescription": " Win 100% Welcome Bonus ", "price": "ACTIVATE OFFER"}, {"dealImage": "data:image/png;base64,R0lGODlhAQABAAD/ACwAAAAAAQABAAACADs=", "rating": "3", "title": " Best Price ", "dealUrl": "https://www.grabon.in/coupon-codes/13354", "provider": "Grabon", "shortDescription": " FREE Rummy On The Go! ", "price": "ACTIVATE OFFER"}, {"dealImage": "data:image/png;base64,R0lGODlhAQABAAD/ACwAAAAAAQABAAACADs=", "rating": "3", "title": " Best Price ", "dealUrl": "https://www.grabon.in/coupon-codes/14175", "provider": "Grabon", "shortDescription": " Buy PopCorn & Coke @ Rs 148 ", "price": "ACTIVATE OFFER"}, {"dealImage": "data:image/png;base64,R0lGODlhAQABAAD/ACwAAAAAAQABAAACADs=", "rating": "4", "title": " Best Price ", "dealUrl": "https://www.grabon.in/coupon-codes/14846", "provider": "Grabon", "shortDescription": " Book Movies Tickets In Hyderabad & Warangal ", "price": "ACTIVATE OFFER"}, {"dealImage": "data:image/png;base64,R0lGODlhAQABAAD/ACwAAAAAAQABAAACADs=", "rating": "4", "title": " Best Price ", "dealUrl": "https://www.grabon.in/coupon-codes/19120", "provider": "Grabon", "shortDescription": " Book Movie Ticket in Bangalore and Get Best Price on Your Booking ", "price": "ACTIVATE OFFER"}, {"dealImage": "data:image/png;base64,R0lGODlhAQABAAD/ACwAAAAAAQABAAACADs=", "rating": "3", "title": " Best Price ", "dealUrl": "https://www.grabon.in/coupon-codes/20667", "provider": "Grabon", "shortDescription": " Chennai: Movie Tickets @ Best Price ", "price": "ACTIVATE OFFER"}, {"dealImage": "data:image/png;base64,R0lGODlhAQABAAD/ACwAAAAAAQABAAACADs=", "rating": "4", "title": " Buy 1 Get 1 Free ", "dealUrl": "https://www.grabon.in/coupon-codes/5002", "provider": "Grabon", "shortDescription": " Buy 1 Get 1 Free With RBL Bank Credit Cards ", "price": "ACTIVATE OFFER"}, {"dealImage": "data:image/png;base64,R0lGODlhAQABAAD/ACwAAAAAAQABAAACADs=", "rating": "4", "title": " Buy 1 Get 1 Free ", "dealUrl": "https://www.grabon.in/coupon-codes/5004", "provider": "Grabon", "shortDescription": " Buy 1 Get 1 Free on Movie Tickets With ICICI Bank Credit Cards ", "price": "ACTIVATE OFFER"}, {"dealImage": "data:image/png;base64,R0lGODlhAQABAAD/ACwAAAAAAQABAAACADs=", "rating": "3", "title": " Buy 1 Get 1 Free ", "dealUrl": "https://www.grabon.in/coupon-codes/6062", "provider": "Grabon", "shortDescription": " Kotak Mahindra Bank Users: Buy 1 Ticket Get 1 Free (Saturdays) ", "price": "ACTIVATE OFFER"}, {"dealImage": "data:image/png;base64,R0lGODlhAQABAAD/ACwAAAAAAQABAAACADs=", "rating": "5", "title": " Buy 1 Get 1 Free ", "dealUrl": "https://www.grabon.in/coupon-codes/10371", "provider": "Grabon", "shortDescription": " ICICI Bank Debit Cards Offer | Buy 1 Get 1 Free Movie Ticket ", "price": "ACTIVATE OFFER"}, {"dealImage": "data:image/png;base64,R0lGODlhAQABAAD/ACwAAAAAAQABAAACADs=", "rating": "4", "title": " Buy 1 Get 1 Free ", "dealUrl": "https://www.grabon.in/coupon-codes/10853", "provider": "Grabon", "shortDescription": " Buy 1 Get 1 Movie Ticket Free on Citibank World Debit Card ", "price": "ACTIVATE OFFER"}, {"dealImage": "data:image/png;base64,R0lGODlhAQABAAD/ACwAAAAAAQABAAACADs=", "rating": "5", "title": " Buy 1 Get 1 Free ", "dealUrl": "https://www.grabon.in/coupon-codes/10870", "provider": "Grabon", "shortDescription": " Buy 1 Get 1 Free On Movie Tickets With Indusind Bank Credit Cards ", "price": "ACTIVATE OFFER"}, {"dealImage": "data:image/png;base64,R0lGODlhAQABAAD/ACwAAAAAAQABAAACADs=", "rating": "4", "title": " Buy 1 Get 1 Free ", "dealUrl": "https://www.grabon.in/coupon-codes/12873", "provider": "Grabon", "shortDescription": " Buy 1 Get 1 Movie Ticket Free (Axis Bank Users) ", "price": "ACTIVATE OFFER"}, {"dealImage": "data:image/png;base64,R0lGODlhAQABAAD/ACwAAAAAAQABAAACADs=", "rating": "3", "title": " Buy 1 Get 1 Free ", "dealUrl": "https://www.grabon.in/coupon-codes/14769", "provider": "Grabon", "shortDescription": " Movie Tickets: Buy 1 Get 1 Free (ICICI Bank Users) ", "price": "ACTIVATE OFFER"}, {"dealImage": "data:image/png;base64,R0lGODlhAQABAAD/ACwAAAAAAQABAAACADs=", "rating": "4", "title": " Buy 1 Get 1 Free ", "dealUrl": "https://www.grabon.in/coupon-codes/18314", "provider": "Grabon", "shortDescription": " IDBI Bank Credit Cards: Buy 1 Ticket and Get 1 Free ", "price": "ACTIVATE OFFER"}, {"dealImage": "data:image/png;base64,R0lGODlhAQABAAD/ACwAAAAAAQABAAACADs=", "rating": "3", "title": " Buy 1 Get 1 Free ", "dealUrl": "https://www.grabon.in/coupon-codes/18315", "provider": "Grabon", "shortDescription": " HSBC's Saturday Offer - Buy 1 Get 1 ", "price": "ACTIVATE OFFER"}, {"dealImage": "data:image/png;base64,R0lGODlhAQABAAD/ACwAAAAAAQABAAACADs=", "rating": "4", "title": " Buy 1 Get 1 Free ", "dealUrl": "https://www.grabon.in/coupon-codes/19267", "provider": "Grabon", "shortDescription": " IndusInd Debit Cards : Buy 1 Get 1 Movie Ticket Free ", "price": "ACTIVATE OFFER"}, {"dealImage": "data:image/png;base64,R0lGODlhAQABAAD/ACwAAAAAAQABAAACADs=", "rating": "3", "title": " Buy 1 Get 1 Free ", "dealUrl": "https://www.grabon.in/coupon-codes/20617", "provider": "Grabon", "shortDescription": " Buy 1 Get 1 Free Through ICICI Bank Debit Cards ", "price": "ACTIVATE OFFER"}, {"dealImage": "data:image/png;base64,R0lGODlhAQABAAD/ACwAAAAAAQABAAACADs=", "rating": "5", "title": " Cashback ", "dealUrl": "https://www.grabon.in/coupon-codes/21281", "provider": "Grabon", "shortDescription": " Get Flat 50% Cashback Using BookMyShow MyWallet ", "price": "ACTIVATE OFFER"}, {"dealImage": "data:image/png;base64,R0lGODlhAQABAAD/ACwAAAAAAQABAAACADs=", "rating": "3", "title": " Hot Deal ", "dealUrl": "https://www.grabon.in/coupon-codes/4896", "provider": "Grabon", "shortDescription": " Entertainment Packages : Starting at \u20b985 ", "price": "ACTIVATE OFFER"}, {"dealImage": "data:image/png;base64,R0lGODlhAQABAAD/ACwAAAAAAQABAAACADs=", "rating": "4", "title": " Hot Deal ", "dealUrl": "https://www.grabon.in/coupon-codes/10470", "provider": "Grabon", "shortDescription": " Book NTR Kathanayakudu Movie Tickets at Lowest Price ", "price": "ACTIVATE OFFER"}, {"dealImage": "data:image/png;base64,R0lGODlhAQABAAD/ACwAAAAAAQABAAACADs=", "rating": "4", "title": " Hot Deal ", "dealUrl": "https://www.grabon.in/coupon-codes/11808", "provider": "Grabon", "shortDescription": " Referral Offer - Earn up to Rs 1000 ", "price": "ACTIVATE OFFER"}, {"dealImage": "data:image/png;base64,R0lGODlhAQABAAD/ACwAAAAAAQABAAACADs=", "rating": "4", "title": " Hot Deal ", "dealUrl": "https://www.grabon.in/coupon-codes/13705", "provider": "Grabon", "shortDescription": " Buy Top Songs @ Rs 9 ", "price": "ACTIVATE OFFER"}, {"dealImage": "data:image/png;base64,R0lGODlhAQABAAD/ACwAAAAAAQABAAACADs=", "rating": "4", "title": " Hot Deal ", "dealUrl": "https://www.grabon.in/coupon-codes/19717", "provider": "Grabon", "shortDescription": " Use WINPIN: Get Bookmyshow Free Movie Tickets ", "price": "ACTIVATE OFFER"}, {"dealImage": "data:image/png;base64,R0lGODlhAQABAAD/ACwAAAAAAQABAAACADs=", "rating": "4", "title": " Hot Deal ", "dealUrl": "https://www.grabon.in/coupon-codes/20514", "provider": "Grabon", "shortDescription": " Friday Tournament: Play Free win Rs. 10,000 ", "price": "ACTIVATE OFFER"}, {"dealImage": "data:image/png;base64,R0lGODlhAQABAAD/ACwAAAAAAQABAAACADs=", "rating": "3", "title": " Hot Deal ", "dealUrl": "https://www.grabon.in/coupon-codes/20592", "provider": "Grabon", "shortDescription": " RBL Bank Offer: Get 2 Movie Tickets Free Every Month ", "price": "ACTIVATE OFFER"}, {"dealImage": "data:image/png;base64,R0lGODlhAQABAAD/ACwAAAAAAQABAAACADs=", "rating": "4", "title": " Rs.100 off ", "dealUrl": "https://www.grabon.in/coupon-codes/43233", "provider": "Grabon", "shortDescription": " Up to \u20b9100 Cashback On All Movie Tickets - New Users ", "price": "TICKET100"}, {"dealImage": "data:image/png;base64,R0lGODlhAQABAAD/ACwAAAAAAQABAAACADs=", "rating": "4", "title": " Rs.100 off ", "dealUrl": "https://www.grabon.in/coupon-codes/10852", "provider": "Grabon", "shortDescription": " Get Rs 100 OFF on Citibank Platinum Debit Card ", "price": "ACTIVATE OFFER"}, {"dealImage": "data:image/png;base64,R0lGODlhAQABAAD/ACwAAAAAAQABAAACADs=", "rating": "3", "title": " Rs.100 off ", "dealUrl": "https://www.grabon.in/coupon-codes/10860", "provider": "Grabon", "shortDescription": " Get Rs 100 OFF on Yes Bank Debit cards ", "price": "ACTIVATE OFFER"}, {"dealImage": "data:image/png;base64,R0lGODlhAQABAAD/ACwAAAAAAQABAAACADs=", "rating": "3", "title": " Rs.1000 off ", "dealUrl": "https://www.grabon.in/coupon-codes/11131", "provider": "Grabon", "shortDescription": " Cash Tournament: Win Up To Rs 1000 Daily ", "price": "ACTIVATE OFFER"}, {"dealImage": "data:image/png;base64,R0lGODlhAQABAAD/ACwAAAAAAQABAAACADs=", "rating": "3", "title": " Rs.150 off ", "dealUrl": "https://www.grabon.in/coupon-codes/17675", "provider": "Grabon", "shortDescription": " Paytm Offer: Flat Rs 150 Cashback On KGF Movie Tickets For First 3 Transactions ", "price": "ACTIVATE OFFER"}, {"dealImage": "data:image/png;base64,R0lGODlhAQABAAD/ACwAAAAAAQABAAACADs=", "rating": "4", "title": " Rs.150 off ", "dealUrl": "https://www.grabon.in/coupon-codes/21161", "provider": "Grabon", "shortDescription": " Up to \u20b9150 SuperCash on Movie Tickets Using Mobikwik Wallet ", "price": "ACTIVATE OFFER"}, {"dealImage": "https://cdn.grabon.in/gograbon/images/merchant/1545148346799/paytm-movies-logo.jpeg", "rating": "3", "title": " Rs.200 off ", "dealUrl": "https://www.grabon.in/coupon-codes/35598", "provider": "Grabon", "shortDescription": " Up to Rs 200 Cashback On Next Movie Tickets - All Users ", "price": "NEXTMOVIE"}, {"dealImage": "data:image/png;base64,R0lGODlhAQABAAD/ACwAAAAAAQABAAACADs=", "rating": "5", "title": " Rs.50 Cashback ", "dealUrl": "https://www.grabon.in/coupon-codes/20432", "provider": "Grabon", "shortDescription": " Buy Movie Tickets and Get \u20b950 Cashback ", "price": "ACTIVATE OFFER"}, {"dealImage": "data:image/png;base64,R0lGODlhAQABAAD/ACwAAAAAAQABAAACADs=", "rating": "3", "title": " Rs.5000 off ", "dealUrl": "https://www.grabon.in/coupon-codes/11778", "provider": "Grabon", "shortDescription": " Welcome Bonus Rs 5000 - Junglee Rummy ", "price": "WIN5000"}, {"dealImage": "data:image/png;base64,R0lGODlhAQABAAD/ACwAAAAAAQABAAACADs=", "rating": "3", "title": " Rs.750 off ", "dealUrl": "https://www.grabon.in/coupon-codes/21094", "provider": "Grabon", "shortDescription": " Idea Matinee: Get Rs 750 Off On Matinee Shows ", "price": "ACTIVATE OFFER"}]}